{"nodes": [{"id": "e_apni_factory_apnifactorycrm_core_admin_py", "label": "admin.py", "file_type": "code", "source_file": "E:\\APNI FACTORY\\ApniFactoryCRM\\core\\admin.py", "source_location": "L1"}], "edges": [{"source": "e_apni_factory_apnifactorycrm_core_admin_py", "target": "django_contrib", "relation": "imports_from", "confidence": "EXTRACTED", "source_file": "E:\\APNI FACTORY\\ApniFactoryCRM\\core\\admin.py", "source_location": "L1", "weight": 1.0}, {"source": "e_apni_factory_apnifactorycrm_core_admin_py", "target": "core_models", "relation": "imports_from", "confidence": "EXTRACTED", "source_file": "E:\\APNI FACTORY\\ApniFactoryCRM\\core\\admin.py", "source_location": "L3", "weight": 1.0}], "raw_calls": []}