{"nodes": [{"id": "e_apni_factory_apnifactorycrm_staticfiles_assets_js_pages_report_details_js", "label": "report-details.js", "file_type": "code", "source_file": "E:\\APNI FACTORY\\ApniFactoryCRM\\staticfiles\\assets\\js\\pages\\report-details.js", "source_location": "L1"}, {"id": "pages_report_details_echartsetoption", "label": "echartSetOption()", "file_type": "code", "source_file": "E:\\APNI FACTORY\\ApniFactoryCRM\\staticfiles\\assets\\js\\pages\\report-details.js", "source_location": "L6"}, {"id": "pages_report_details_reportsdetailschartinit", "label": "reportsDetailsChartInit()", "file_type": "code", "source_file": "E:\\APNI FACTORY\\ApniFactoryCRM\\staticfiles\\assets\\js\\pages\\report-details.js", "source_location": "L8"}], "edges": [{"source": "e_apni_factory_apnifactorycrm_staticfiles_assets_js_pages_report_details_js", "target": "pages_report_details_echartsetoption", "relation": "contains", "confidence": "EXTRACTED", "source_file": "E:\\APNI FACTORY\\ApniFactoryCRM\\staticfiles\\assets\\js\\pages\\report-details.js", "source_location": "L6", "weight": 1.0}, {"source": "e_apni_factory_apnifactorycrm_staticfiles_assets_js_pages_report_details_js", "target": "pages_report_details_reportsdetailschartinit", "relation": "contains", "confidence": "EXTRACTED", "source_file": "E:\\APNI FACTORY\\ApniFactoryCRM\\staticfiles\\assets\\js\\pages\\report-details.js", "source_location": "L8", "weight": 1.0}, {"source": "pages_report_details_reportsdetailschartinit", "target": "pages_report_details_echartsetoption", "relation": "calls", "confidence": "EXTRACTED", "source_file": "E:\\APNI FACTORY\\ApniFactoryCRM\\staticfiles\\assets\\js\\pages\\report-details.js", "source_location": "L8", "weight": 1.0}], "raw_calls": [{"caller_nid": "pages_report_details_echartsetoption", "callee": "setOption", "source_file": "E:\\APNI FACTORY\\ApniFactoryCRM\\staticfiles\\assets\\js\\pages\\report-details.js", "source_location": "L6"}, {"caller_nid": "pages_report_details_echartsetoption", "callee": "merge", "source_file": "E:\\APNI FACTORY\\ApniFactoryCRM\\staticfiles\\assets\\js\\pages\\report-details.js", "source_location": "L6"}, {"caller_nid": "pages_report_details_echartsetoption", "callee": "s", "source_file": "E:\\APNI FACTORY\\ApniFactoryCRM\\staticfiles\\assets\\js\\pages\\report-details.js", "source_location": "L6"}, {"caller_nid": "pages_report_details_echartsetoption", "callee": "querySelector", "source_file": "E:\\APNI FACTORY\\ApniFactoryCRM\\staticfiles\\assets\\js\\pages\\report-details.js", "source_location": "L6"}, {"caller_nid": "pages_report_details_echartsetoption", "callee": "addEventListener", "source_file": "E:\\APNI FACTORY\\ApniFactoryCRM\\staticfiles\\assets\\js\\pages\\report-details.js", "source_location": "L6"}, {"caller_nid": "pages_report_details_echartsetoption", "callee": "a", "source_file": "E:\\APNI FACTORY\\ApniFactoryCRM\\staticfiles\\assets\\js\\pages\\report-details.js", "source_location": "L6"}, {"caller_nid": "pages_report_details_echartsetoption", "callee": "l", "source_file": "E:\\APNI FACTORY\\ApniFactoryCRM\\staticfiles\\assets\\js\\pages\\report-details.js", "source_location": "L6"}, {"caller_nid": "pages_report_details_echartsetoption", "callee": "addEventListener", "source_file": "E:\\APNI FACTORY\\ApniFactoryCRM\\staticfiles\\assets\\js\\pages\\report-details.js", "source_location": "L6"}, {"caller_nid": "pages_report_details_reportsdetailschartinit", "callee": "querySelector", "source_file": "E:\\APNI FACTORY\\ApniFactoryCRM\\staticfiles\\assets\\js\\pages\\report-details.js", "source_location": "L8"}, {"caller_nid": "pages_report_details_reportsdetailschartinit", "callee": "o", "source_file": "E:\\APNI FACTORY\\ApniFactoryCRM\\staticfiles\\assets\\js\\pages\\report-details.js", "source_location": "L8"}, {"caller_nid": "pages_report_details_reportsdetailschartinit", "callee": "init", "source_file": "E:\\APNI FACTORY\\ApniFactoryCRM\\staticfiles\\assets\\js\\pages\\report-details.js", "source_location": "L8"}]}